close_mongo_ops_manager/__init__.py
close_mongo_ops_manager/app.py
close_mongo_ops_manager/config_manager.py
close_mongo_ops_manager/exceptions.py
close_mongo_ops_manager/filterbar.py
close_mongo_ops_manager/help_screen.py
close_mongo_ops_manager/kill_confirmation_screen.py
close_mongo_ops_manager/log_screen.py
close_mongo_ops_manager/messages.py
close_mongo_ops_manager/mongodb_manager.py
close_mongo_ops_manager/operation_details_screen.py
close_mongo_ops_manager/operations_view.py
close_mongo_ops_manager/statusbar.py
close_mongo_ops_manager/theme_manager.py
close_mongo_ops_manager/theme_screen.py
close_mongo_ops_manager-0.5.4.dist-info/WHEEL
close_mongo_ops_manager-0.5.4.dist-info/entry_points.txt
close_mongo_ops_manager-0.5.4.dist-info/METADATA
close_mongo_ops_manager-0.5.4.dist-info/RECORD
