Metadata-Version: 2.4
Name: close-mongo-ops-manager
Version: 0.5.4
Summary: Monitor and kill MongoDB operations
Keywords: mongo,operations,manager
Author: Vicenç Juan Tomàs Monserrat
Author-email: Vicenç Juan Tomàs Monserrat <vicenc.monserrat@close.com>
License-Expression: MIT
Classifier: Development Status :: 4 - Beta
Classifier: Environment :: Console
Classifier: Intended Audience :: Developers
Classifier: Operating System :: POSIX
Classifier: License :: OSI Approved :: MIT License
Classifier: Programming Language :: Python
Classifier: Programming Language :: Python :: 3.12
Classifier: Programming Language :: Python :: 3.13
Classifier: Programming Language :: Python :: 3.14
Classifier: Programming Language :: Python :: 3 :: Only
Classifier: Topic :: Database :: Front-Ends
Requires-Dist: pymongo==4.15.3,<4.16.0
Requires-Dist: textual>=6.0.0,<7.0.0
Requires-Python: >=3.12
Project-URL: Documentation, https://github.com/closeio/close-mongo-ops-manager#readme
Project-URL: Issues, https://github.com/closeio/close-mongo-ops-manager/issues
Project-URL: Source, https://github.com/closeio/close-mongo-ops-manager
